<?xml version="1.0" encoding="UTF-8"?>
<collection xmlns="http://www.loc.gov/MARC21/slim">
    <record>
        <leader>00000cas a22000003 4500</leader>
        <controlfield tag="001">test_id_2</controlfield>
        <datafield tag="776" ind1="0" ind2="8">
            <subfield code="i">Online version:</subfield>
            <subfield code="t">Behavioural processes (Online)</subfield>
            <subfield code="w">(DLC) 2002238501</subfield>
            <subfield code="w">(OCoLC)38491814</subfield>
        </datafield>
    </record>
</collection>
